anndash/__init__.py
anndash/_modidx.py
anndash/color.py
anndash/core.py
anndash/enums.py
anndash/env.yml
anndash/hints.py
anndash/plots.py
anndash/utils.py
anndash-0.0.9.dist-info/LICENSE
anndash-0.0.9.dist-info/METADATA
anndash-0.0.9.dist-info/WHEEL
anndash-0.0.9.dist-info/entry_points.txt
anndash-0.0.9.dist-info/top_level.txt
anndash-0.0.9.dist-info/RECORD
