Metadata-Version: 2.1
Name: anndash
Version: 0.0.9
Home-page: https://github.com/dsm-72/anndash
Author: dsm-72
Author-email: sumner.magruder@yale.edu
License: Apache Software License 2.0
Keywords: anndash anndata omics genomics transcriptomics pipseq spatial plotly dash
Classifier: Development Status :: 4 - Beta
Classifier: Intended Audience :: Developers
Classifier: Natural Language :: English
Classifier: Programming Language :: Python :: 3.10
Classifier: Programming Language :: Python :: 3.11
Classifier: Programming Language :: Python :: 3.12
Classifier: Programming Language :: Python :: 3.13
Classifier: License :: OSI Approved :: Apache Software License
Requires-Python: >=3.10
License-File: LICENSE
Requires-Dist: typing-extensions
Requires-Dist: tqdm
Requires-Dist: pyyaml
Requires-Dist: notebook
Requires-Dist: ipykernel
Requires-Dist: ipywidgets
Requires-Dist: jupyterlab
Requires-Dist: nbdev>=2.3.12
Requires-Dist: scikit-learn
Requires-Dist: pandas
Requires-Dist: numpy
Requires-Dist: matplotlib
Requires-Dist: seaborn
Requires-Dist: plotly
Requires-Dist: dash
Requires-Dist: plotly-express
Requires-Dist: dash-bootstrap-components
Requires-Dist: scanpy
Requires-Dist: anndata
Provides-Extra: dev
